Workbook

Sheet How to use
A1: Job and payment tracker
A2: A free template from A2B Guides. Not legal, tax or financial advice.
A4: What this does
A5: One row per job: quoted, invoiced, paid. It works out what you are owed, what is overdue and how much you invoiced each month.
A6: Which cells to fill in
A7: Yellow cells are yours to fill in, including your payment terms on the Summary sheet. Grey cells work themselves out.
A8: The green row is an example. Delete or overwrite it.
A9: Late payment
A10: For business customers, GOV.UK sets out statutory interest and fixed recovery sums for late payment. GOV.UK does not describe these as applying to householders. Read the guide before using them:
A11: https://www.gov.uk/late-commercial-payments-interest-debt-recovery
A12: Related guides
A13: https://a2bguides.github.io/guides/quote-invoice-templates/
... A15: When you outgrow a spreadsheet, the job-management apps guide compares paid options.

Sheet Jobs
A1: Jobs
A2: One row per job. Status updates itself.
A4: Job ref | B4: Customer | C4: Postcode | D4: Start date | E4: Finish date | F4: Quoted (£) | G4: Invoice no. | H4: Invoice date | I4: Invoiced (£) | J4: Due date | K4: Paid (£) | L4: Date paid | M4: Outstanding (£) | N4: Status
A5: J001 | B5: Sam Customer | C5: EX2 2BB | D5: 46310 | E5: 46310 | F5: 188 | G5: 0001 | H5: 46315 | I5: 188 | J5: =IF(H5="","",H5+Summary!$B$4) -> 46329 | K5: 188 | L5: 46323 | M5: =IF(I5="","",I5-N(K5)) -> 0 | N5: =IF(A5="","",IF(I5="",IF(E5<>"","To invoice","In progress"),IF(M5<=0,"Paid",IF(TODAY()>J5,"Overdue","Awaiting payment")))) -> Paid
J6: =IF(H6="","",H6+Summary!$B$4) | M6: =IF(I6="","",I6-N(K6)) | N6: =IF(A6="","",IF(I6="",IF(E6<>"","To invoice","In progress"),IF(M6<=0,"Paid",IF(TODAY()>J6,"Overdue","Awaiting payment"))))
J7: =IF(H7="","",H7+Summary!$B$4) | M7: =IF(I7="","",I7-N(K7)) | N7: =IF(A7="","",IF(I7="",IF(E7<>"","To invoice","In progress"),IF(M7<=0,"Paid",IF(TODAY()>J7,"Overdue","Awaiting payment"))))
J8: =IF(H8="","",H8+Summary!$B$4) | M8: =IF(I8="","",I8-N(K8)) | N8: =IF(A8="","",IF(I8="",IF(E8<>"","To invoice","In progress"),IF(M8<=0,"Paid",IF(TODAY()>J8,"Overdue","Awaiting payment"))))
J9: =IF(H9="","",H9+Summary!$B$4) | M9: =IF(I9="","",I9-N(K9)) | N9: =IF(A9="","",IF(I9="",IF(E9<>"","To invoice","In progress"),IF(M9<=0,"Paid",IF(TODAY()>J9,"Overdue","Awaiting payment"))))
J10: =IF(H10="","",H10+Summary!$B$4) | M10: =IF(I10="","",I10-N(K10)) | N10: =IF(A10="","",IF(I10="",IF(E10<>"","To invoice","In progress"),IF(M10<=0,"Paid",IF(TODAY()>J10,"Overdue","Awaiting payment"))))
J11: =IF(H11="","",H11+Summary!$B$4) | M11: =IF(I11="","",I11-N(K11)) | N11: =IF(A11="","",IF(I11="",IF(E11<>"","To invoice","In progress"),IF(M11<=0,"Paid",IF(TODAY()>J11,"Overdue","Awaiting payment"))))
J12: =IF(H12="","",H12+Summary!$B$4) | M12: =IF(I12="","",I12-N(K12)) | N12: =IF(A12="","",IF(I12="",IF(E12<>"","To invoice","In progress"),IF(M12<=0,"Paid",IF(TODAY()>J12,"Overdue","Awaiting payment"))))
J13: =IF(H13="","",H13+Summary!$B$4) | M13: =IF(I13="","",I13-N(K13)) | N13: =IF(A13="","",IF(I13="",IF(E13<>"","To invoice","In progress"),IF(M13<=0,"Paid",IF(TODAY()>J13,"Overdue","Awaiting payment"))))
J14: =IF(H14="","",H14+Summary!$B$4) | M14: =IF(I14="","",I14-N(K14)) | N14: =IF(A14="","",IF(I14="",IF(E14<>"","To invoice","In progress"),IF(M14<=0,"Paid",IF(TODAY()>J14,"Overdue","Awaiting payment"))))
J15: =IF(H15="","",H15+Summary!$B$4) | M15: =IF(I15="","",I15-N(K15)) | N15: =IF(A15="","",IF(I15="",IF(E15<>"","To invoice","In progress"),IF(M15<=0,"Paid",IF(TODAY()>J15,"Overdue","Awaiting payment"))))
J16: =IF(H16="","",H16+Summary!$B$4) | M16: =IF(I16="","",I16-N(K16)) | N16: =IF(A16="","",IF(I16="",IF(E16<>"","To invoice","In progress"),IF(M16<=0,"Paid",IF(TODAY()>J16,"Overdue","Awaiting payment"))))
J17: =IF(H17="","",H17+Summary!$B$4) | M17: =IF(I17="","",I17-N(K17)) | N17: =IF(A17="","",IF(I17="",IF(E17<>"","To invoice","In progress"),IF(M17<=0,"Paid",IF(TODAY()>J17,"Overdue","Awaiting payment"))))
... J504: =IF(H504="","",H504+Summary!$B$4) | M504: =IF(I504="","",I504-N(K504)) | N504: =IF(A504="","",IF(I504="",IF(E504<>"","To invoice","In progress"),IF(M504<=0,"Paid",IF(TODAY()>J504,"Overdue","Awaiting payment"))))

Sheet Summary
A1: Summary
A2: Everything here works itself out from the Jobs sheet, apart from the yellow cells.
A4: Payment terms (days) | B4: 14
A5: Year for the monthly table | B5: 2026
A7: Invoiced (all time) | B7: =SUM(Jobs!I5:I504) -> 188
A8: Paid (all time) | B8: =SUM(Jobs!K5:K504) -> 188
A9: Owed to you now | B9: =SUMIFS(Jobs!M5:M504,Jobs!N5:N504,"Awaiting payment")+SUMIFS(Jobs!M5:M504,Jobs!N5:N504,"Overdue") -> 0
A10: Of which overdue | B10: =SUMIFS(Jobs!M5:M504,Jobs!N5:N504,"Overdue") -> 0
A11: Jobs finished but not invoiced | B11: =COUNTIF(Jobs!N5:N504,"To invoice") -> 0
A13: Month | B13: Invoiced (£) | C13: Paid (£)
A14: =DATE($B$5,1,1) -> 46023 | B14: =SUMIFS(Jobs!$I$5:$I$504,Jobs!$H$5:$H$504,">="&A14,Jobs!$H$5:$H$504,"<"&EDATE(A14,1)) -> 0 | C14: =SUMIFS(Jobs!$K$5:$K$504,Jobs!$L$5:$L$504,">="&A14,Jobs!$L$5:$L$504,"<"&EDATE(A14,1)) -> 0
A15: =DATE($B$5,2,1) -> 46054 | B15: =SUMIFS(Jobs!$I$5:$I$504,Jobs!$H$5:$H$504,">="&A15,Jobs!$H$5:$H$504,"<"&EDATE(A15,1)) -> 0 | C15: =SUMIFS(Jobs!$K$5:$K$504,Jobs!$L$5:$L$504,">="&A15,Jobs!$L$5:$L$504,"<"&EDATE(A15,1)) -> 0
A16: =DATE($B$5,3,1) -> 46082 | B16: =SUMIFS(Jobs!$I$5:$I$504,Jobs!$H$5:$H$504,">="&A16,Jobs!$H$5:$H$504,"<"&EDATE(A16,1)) -> 0 | C16: =SUMIFS(Jobs!$K$5:$K$504,Jobs!$L$5:$L$504,">="&A16,Jobs!$L$5:$L$504,"<"&EDATE(A16,1)) -> 0
A17: =DATE($B$5,4,1) -> 46113 | B17: =SUMIFS(Jobs!$I$5:$I$504,Jobs!$H$5:$H$504,">="&A17,Jobs!$H$5:$H$504,"<"&EDATE(A17,1)) -> 0 | C17: =SUMIFS(Jobs!$K$5:$K$504,Jobs!$L$5:$L$504,">="&A17,Jobs!$L$5:$L$504,"<"&EDATE(A17,1)) -> 0
A18: =DATE($B$5,5,1) -> 46143 | B18: =SUMIFS(Jobs!$I$5:$I$504,Jobs!$H$5:$H$504,">="&A18,Jobs!$H$5:$H$504,"<"&EDATE(A18,1)) -> 0 | C18: =SUMIFS(Jobs!$K$5:$K$504,Jobs!$L$5:$L$504,">="&A18,Jobs!$L$5:$L$504,"<"&EDATE(A18,1)) -> 0
A19: =DATE($B$5,6,1) -> 46174 | B19: =SUMIFS(Jobs!$I$5:$I$504,Jobs!$H$5:$H$504,">="&A19,Jobs!$H$5:$H$504,"<"&EDATE(A19,1)) -> 0 | C19: =SUMIFS(Jobs!$K$5:$K$504,Jobs!$L$5:$L$504,">="&A19,Jobs!$L$5:$L$504,"<"&EDATE(A19,1)) -> 0
A20: =DATE($B$5,7,1) -> 46204 | B20: =SUMIFS(Jobs!$I$5:$I$504,Jobs!$H$5:$H$504,">="&A20,Jobs!$H$5:$H$504,"<"&EDATE(A20,1)) -> 0 | C20: =SUMIFS(Jobs!$K$5:$K$504,Jobs!$L$5:$L$504,">="&A20,Jobs!$L$5:$L$504,"<"&EDATE(A20,1)) -> 0
A21: =DATE($B$5,8,1) -> 46235 | B21: =SUMIFS(Jobs!$I$5:$I$504,Jobs!$H$5:$H$504,">="&A21,Jobs!$H$5:$H$504,"<"&EDATE(A21,1)) -> 0 | C21: =SUMIFS(Jobs!$K$5:$K$504,Jobs!$L$5:$L$504,">="&A21,Jobs!$L$5:$L$504,"<"&EDATE(A21,1)) -> 0
A22: =DATE($B$5,9,1) -> 46266 | B22: =SUMIFS(Jobs!$I$5:$I$504,Jobs!$H$5:$H$504,">="&A22,Jobs!$H$5:$H$504,"<"&EDATE(A22,1)) -> 0 | C22: =SUMIFS(Jobs!$K$5:$K$504,Jobs!$L$5:$L$504,">="&A22,Jobs!$L$5:$L$504,"<"&EDATE(A22,1)) -> 0
A23: =DATE($B$5,10,1) -> 46296 | B23: =SUMIFS(Jobs!$I$5:$I$504,Jobs!$H$5:$H$504,">="&A23,Jobs!$H$5:$H$504,"<"&EDATE(A23,1)) -> 188 | C23: =SUMIFS(Jobs!$K$5:$K$504,Jobs!$L$5:$L$504,">="&A23,Jobs!$L$5:$L$504,"<"&EDATE(A23,1)) -> 188
A24: =DATE($B$5,11,1) -> 46327 | B24: =SUMIFS(Jobs!$I$5:$I$504,Jobs!$H$5:$H$504,">="&A24,Jobs!$H$5:$H$504,"<"&EDATE(A24,1)) -> 0 | C24: =SUMIFS(Jobs!$K$5:$K$504,Jobs!$L$5:$L$504,">="&A24,Jobs!$L$5:$L$504,"<"&EDATE(A24,1)) -> 0
A25: =DATE($B$5,12,1) -> 46357 | B25: =SUMIFS(Jobs!$I$5:$I$504,Jobs!$H$5:$H$504,">="&A25,Jobs!$H$5:$H$504,"<"&EDATE(A25,1)) -> 0 | C25: =SUMIFS(Jobs!$K$5:$K$504,Jobs!$L$5:$L$504,">="&A25,Jobs!$L$5:$L$504,"<"&EDATE(A25,1)) -> 0
A26: Year total | B26: =SUM(B14:B25) -> 188 | C26: =SUM(C14:C25) -> 188
