Workbook

Sheet How to use
A1: Quote and invoice workbook
A2: A free template from A2B Guides. Not legal, tax or financial advice.
A4: What this does
A5: Fill in your details once, then write a quote and turn it into an invoice. Totals, VAT (if you are registered) and the payment due date work themselves out. Keep a copy of the workbook for each job, or record each invoice on the Invoice log sheet.
A6: Which cells to fill in
A7: Yellow cells are yours to fill in. Grey cells work themselves out; please leave them alone.
A8: Green rows are examples showing the format. Delete or overwrite them.
A9: What GOV.UK says an invoice must include
A10: A unique identification number; your name or company name, address and contact details; the customer's name and address; a clear description of what you're charging for; the supply date; the invoice date; the amount(s) charged; VAT if applicable; the total amount owed. Sole traders using a business name also need an address where legal documents can be delivered. The Invoice sheet has a place for each.
A11: https://www.gov.uk/invoicing-and-taking-payment-from-customers/invoices-what-they-must-include
A12: If you are VAT registered, a VAT invoice needs more detail (VAT Notice 700/21, section 4.1). Check it and add any lines you need.
A13: https://www.gov.uk/guidance/record-keeping-for-vat-notice-70021
... A20: Rules and rates change. Check GOV.UK before relying on anything here. Last checked 11 October 2026.

Sheet Your details
A1: Your details
A2: Fill these in once. The quote and invoice pull them in automatically.
A4: Your full name | B4: Alex Example
A5: Business name (if you use one) | B5: Example Plumbing
A6: Limited company name (as on the certificate, if a company)
A7: Business address | B7: 1 Example Street, Exampletown, EX1 1AA
A8: Address for legal documents (sole traders using a business name) | B8: 1 Example Street, Exampletown, EX1 1AA
A9: Phone | B9: 07000 000000
A10: Email | B10: hello@example.com
A11: Bank name | B11: Example Bank
A12: Account name | B12: A Example
A13: Sort code | B13: 00-00-00
A14: Account number | B14: 00000000
A15: VAT registered? (Yes/No) | B15: No
A16: VAT registration number
A17: VAT rate (if registered) | B17: 0
A18: Payment terms in days | B18: 14
A20: The example values above show the format. Replace them with your own.

Sheet Quote
A1: QUOTE
C2: Quote number | D2: Q0001
A3: =IF('Your details'!B6<>"",'Your details'!B6,IF('Your details'!B5<>"",'Your details'!B4&" trading as "&'Your details'!B5,'Your details'!B4)) -> Alex Example trading as Example Plumbing | C3: Date of quote | D3: 46307
A4: ='Your details'!B7 -> 1 Example Street, Exampletown, EX1 1AA | C4: Price valid until | D4: 46337
A5: ='Your details'!B9&" · "&'Your details'!B10 -> 07000 000000 · hello@example.com | C5: Expected start | D5: Week of 19 Oct 2026
A6: =IF('Your details'!B15="Yes","VAT number: "&'Your details'!B16,"")
A9: For
A10: Sam Customer
A11: 12 Sample Road, Exampletown, EX2 2BB
A12: Job address (if different)
A14: Description of the work or goods | B14: Qty | C14: Unit price (£) | D14: Line total (£)
A15: Supply and fit kitchen mixer tap | B15: 1 | C15: 85 | D15: =IF(B15="","",B15*C15) -> 85
A16: Labour (hours) | B16: 2 | C16: 45 | D16: =IF(B16="","",B16*C16) -> 90
A17: Isolating valves | B17: 2 | C17: 6.5 | D17: =IF(B17="","",B17*C17) -> 13
D18: =IF(B18="","",B18*C18)
D19: =IF(B19="","",B19*C19)
D20: =IF(B20="","",B20*C20)
D21: =IF(B21="","",B21*C21)
D22: =IF(B22="","",B22*C22)
D23: =IF(B23="","",B23*C23)
D24: =IF(B24="","",B24*C24)
D25: =IF(B25="","",B25*C25)
D26: =IF(B26="","",B26*C26)
C28: Subtotal | D28: =SUM(D15:D26) -> 188
C29: =IF('Your details'!B15="Yes","VAT at "&TEXT('Your details'!B17,"0%"),"VAT (not registered)") -> VAT (not registered) | D29: =IF('Your details'!B15="Yes",ROUND(D28*'Your details'!B17,2),0) -> 0
C30: TOTAL PRICE | D30: =D28+D29 -> 188
A32: What is included
A33: All parts and labour listed above; removal of the old tap
A34: What is not included
A35: Redecoration; any extra work found once started (priced and agreed first)
A36: Payment terms
A37: Balance due within 14 days of the invoice date
A39: To accept, sign and return, or reply by email confirming the quote number. Name: ____________ Signature: ____________ Date: ________

Sheet Invoice
A1: INVOICE
C2: Invoice number | D2: 0001
A3: =IF('Your details'!B6<>"",'Your details'!B6,IF('Your details'!B5<>"",'Your details'!B4&" trading as "&'Your details'!B5,'Your details'!B4)) -> Alex Example trading as Example Plumbing | C3: Invoice date | D3: 46315
A4: ='Your details'!B7 -> 1 Example Street, Exampletown, EX1 1AA | C4: Date work done (supply date) | D4: 46313
A5: ='Your details'!B9&" · "&'Your details'!B10 -> 07000 000000 · hello@example.com | C5: Your quote reference | D5: Q0001
A6: =IF(AND('Your details'!B5<>"",'Your details'!B6=""),"Address for legal documents: "&'Your details'!B8,"") -> Address for legal documents: 1 Example Street, Exampletown, EX1 1AA
A7: =IF('Your details'!B15="Yes","VAT registration number: "&'Your details'!B16,"")
A9: Bill to
A10: Sam Customer
A11: 12 Sample Road, Exampletown, EX2 2BB
A12: Job address (if different)
A14: Description of the work or goods | B14: Qty | C14: Unit price (£) | D14: Line total (£)
A15: Supply and fit kitchen mixer tap | B15: 1 | C15: 85 | D15: =IF(B15="","",B15*C15) -> 85
A16: Labour (hours) | B16: 2 | C16: 45 | D16: =IF(B16="","",B16*C16) -> 90
A17: Isolating valves | B17: 2 | C17: 6.5 | D17: =IF(B17="","",B17*C17) -> 13
D18: =IF(B18="","",B18*C18)
D19: =IF(B19="","",B19*C19)
D20: =IF(B20="","",B20*C20)
D21: =IF(B21="","",B21*C21)
D22: =IF(B22="","",B22*C22)
D23: =IF(B23="","",B23*C23)
D24: =IF(B24="","",B24*C24)
D25: =IF(B25="","",B25*C25)
D26: =IF(B26="","",B26*C26)
C28: Subtotal | D28: =SUM(D15:D26) -> 188
C29: =IF('Your details'!B15="Yes","VAT at "&TEXT('Your details'!B17,"0%"),"VAT (not registered)") -> VAT (not registered) | D29: =IF('Your details'!B15="Yes",ROUND(D28*'Your details'!B17,2),0) -> 0
C30: Less deposit paid | D30: 0
C31: TOTAL AMOUNT OWED | D31: =D28+D29-D30 -> 188
A33: Payment
A34: ="Payment due by: "&TEXT(D3+'Your details'!B18,"dd mmmm yyyy") -> Payment due by: 03 November 2026
A35: ="Pay to: "&'Your details'!B11&", "&'Your details'!B12&", sort code "&'Your details'!B13&", account "&'Your details'!B14 -> Pay to: Example Bank, A Example, sort code 00-00-00, account 00000000
A36: ="Please use invoice number "&D2&" as the payment reference." -> Please use invoice number 0001 as the payment reference.
A38: Thank you for your business.

Sheet Invoice log
A1: Invoice log
A2: One row per invoice. Status updates itself from the dates.
A4: Invoice no. | B4: Invoice date | C4: Customer | D4: Total (£) | E4: Due date | F4: Date paid | G4: Status | H4: Days overdue | J4: Owed to you now
A5: 0001 | B5: 46315 | C5: Sam Customer | D5: 188 | E5: =IF(B5="","",B5+'Your details'!$B$18) -> 46329 | F5: 46323 | G5: =IF(B5="","",IF(F5<>"","Paid",IF(TODAY()>E5,"Overdue","Due"))) -> Paid | H5: =IF(G5="Overdue",TODAY()-E5,"") | J5: =SUMIFS(D5:D204,G5:G204,"Due")+SUMIFS(D5:D204,G5:G204,"Overdue") -> 0
E6: =IF(B6="","",B6+'Your details'!$B$18) | G6: =IF(B6="","",IF(F6<>"","Paid",IF(TODAY()>E6,"Overdue","Due"))) | H6: =IF(G6="Overdue",TODAY()-E6,"") | J6: Of which overdue
E7: =IF(B7="","",B7+'Your details'!$B$18) | G7: =IF(B7="","",IF(F7<>"","Paid",IF(TODAY()>E7,"Overdue","Due"))) | H7: =IF(G7="Overdue",TODAY()-E7,"") | J7: =SUMIFS(D5:D204,G5:G204,"Overdue") -> 0
E8: =IF(B8="","",B8+'Your details'!$B$18) | G8: =IF(B8="","",IF(F8<>"","Paid",IF(TODAY()>E8,"Overdue","Due"))) | H8: =IF(G8="Overdue",TODAY()-E8,"")
E9: =IF(B9="","",B9+'Your details'!$B$18) | G9: =IF(B9="","",IF(F9<>"","Paid",IF(TODAY()>E9,"Overdue","Due"))) | H9: =IF(G9="Overdue",TODAY()-E9,"")
E10: =IF(B10="","",B10+'Your details'!$B$18) | G10: =IF(B10="","",IF(F10<>"","Paid",IF(TODAY()>E10,"Overdue","Due"))) | H10: =IF(G10="Overdue",TODAY()-E10,"")
E11: =IF(B11="","",B11+'Your details'!$B$18) | G11: =IF(B11="","",IF(F11<>"","Paid",IF(TODAY()>E11,"Overdue","Due"))) | H11: =IF(G11="Overdue",TODAY()-E11,"")
E12: =IF(B12="","",B12+'Your details'!$B$18) | G12: =IF(B12="","",IF(F12<>"","Paid",IF(TODAY()>E12,"Overdue","Due"))) | H12: =IF(G12="Overdue",TODAY()-E12,"")
E13: =IF(B13="","",B13+'Your details'!$B$18) | G13: =IF(B13="","",IF(F13<>"","Paid",IF(TODAY()>E13,"Overdue","Due"))) | H13: =IF(G13="Overdue",TODAY()-E13,"")
E14: =IF(B14="","",B14+'Your details'!$B$18) | G14: =IF(B14="","",IF(F14<>"","Paid",IF(TODAY()>E14,"Overdue","Due"))) | H14: =IF(G14="Overdue",TODAY()-E14,"")
E15: =IF(B15="","",B15+'Your details'!$B$18) | G15: =IF(B15="","",IF(F15<>"","Paid",IF(TODAY()>E15,"Overdue","Due"))) | H15: =IF(G15="Overdue",TODAY()-E15,"")
E16: =IF(B16="","",B16+'Your details'!$B$18) | G16: =IF(B16="","",IF(F16<>"","Paid",IF(TODAY()>E16,"Overdue","Due"))) | H16: =IF(G16="Overdue",TODAY()-E16,"")
E17: =IF(B17="","",B17+'Your details'!$B$18) | G17: =IF(B17="","",IF(F17<>"","Paid",IF(TODAY()>E17,"Overdue","Due"))) | H17: =IF(G17="Overdue",TODAY()-E17,"")
E18: =IF(B18="","",B18+'Your details'!$B$18) | G18: =IF(B18="","",IF(F18<>"","Paid",IF(TODAY()>E18,"Overdue","Due"))) | H18: =IF(G18="Overdue",TODAY()-E18,"")
E19: =IF(B19="","",B19+'Your details'!$B$18) | G19: =IF(B19="","",IF(F19<>"","Paid",IF(TODAY()>E19,"Overdue","Due"))) | H19: =IF(G19="Overdue",TODAY()-E19,"")
... E204: =IF(B204="","",B204+'Your details'!$B$18) | G204: =IF(B204="","",IF(F204<>"","Paid",IF(TODAY()>E204,"Overdue","Due"))) | H204: =IF(G204="Overdue",TODAY()-E204,"")
